[
  {
    "id": 1,
    "category": "SeeFood",
    "title": "مأكولات بحريه",
    "amount": 1,
    "price": 5,
    "img": "/assets/seefood.jpg",
    "description": "وجبات سريعه ,ايطالي",
    "addion1": { "state": "0", "content": {} },
    "addion2": { "state": "0", "content": {} },
    "addion3": { "state": "0", "content": {} },
    "addion4": { "state": "0", "content": {} },
    "comment": "",
    "totalPrice": 5,
    "size": "1"
  },
  {
    "id": 2,
    "category": "MostWanted",
    "title": "الاكثر طلبا",
    "amount": 1,
    "price": 5,
    "img": "/assets/SeeFood.jpg",
    "description": "وجبات سريعه ,ايطالي",
    "addion1": { "state": "0", "content": {} },
    "addion2": { "state": "0", "content": {} },
    "addion3": { "state": "0", "content": {} },
    "addion4": { "state": "0", "content": {} },
    "comment": "",
    "totalPrice": 5,
    "size": "1"
  },
  {
    "id": 3,
    "category": "SeeFood",
    "title": "مأكولات بحريه",
    "amount": 1,
    "price": 5,
    "img": "/assets/seefood.jpg",
    "description": "وجبات سريعه ,ايطالي",
    "addion1": { "state": "0", "content": {} },
    "addion2": { "state": "0", "content": {} },
    "addion3": { "state": "0", "content": {} },
    "addion4": { "state": "0", "content": {} },
    "comment": "",
    "totalPrice": 5,
    "size": "1"
  },
  {
    "id": 4,
    "category": "Pizza",
    "title": "بيتزا",
    "amount": 1,
    "price": 5,
    "img": "/assets/petza.jpg",
    "description": "وجبات سريعه ,ايطالي",
    "addion1": { "state": "0", "content": {} },
    "addion2": { "state": "0", "content": {} },
    "addion3": { "state": "0", "content": {} },
    "addion4": { "state": "0", "content": {} },
    "comment": "",
    "totalPrice": 5,
    "size": "1"
  },
  {
    "id": 5,
    "category": "meat",
    "price": 5,
    "amount": 1,
    "title": "لحوم",
    "img": "/assets/meat.jpg",
    "description": "وجبات سريعه ,ايطالي",
    "addion1": { "state": "0", "content": {} },
    "addion2": { "state": "0", "content": {} },
    "addion3": { "state": "0", "content": {} },
    "addion4": { "state": "0", "content": {} },
    "comment": "",
    "totalPrice": 5,
    "size": "1"
  },
  {
    "id": 6,
    "category": "chicken",
    "price": 5,
    "title": "فراخ",
    "amount": 1,
    "img": "/assets/cheken.jpg",
    "description": "وجبات سريعه ,ايطالي",
    "addion1": { "state": "0", "content": {} },
    "addion2": { "state": "0", "content": {} },
    "addion3": { "state": "0", "content": {} },
    "addion4": { "state": "0", "content": {} },
    "comment": "",
    "totalPrice": 5,
    "size": "1"
  },
  {
    "id": 7,
    "category": "sandwichs",
    "title": "ساندوتشات",
    "price": 5,
    "amount": 1,
    "img": "/assets/sandwatch.jpg",
    "description": "وجبات سريعه ,ايطالي",
    "addion1": { "state": "0", "content": {} },
    "addion2": { "state": "0", "content": {} },
    "addion3": { "state": "0", "content": {} },
    "addion4": { "state": "0", "content": {} },
    "comment": "",
    "totalPrice": 5,
    "size": "1"
  },
  {
    "id": 8,
    "category": "Burger",
    "amount": 1,
    "title": "برجر",
    "price": 5,
    "img": "/assets/برجر.jpg",
    "description": "وجبات سريعه ,ايطالي",
    "addion1": { "state": "0", "content": {} },
    "addion2": { "state": "0", "content": {} },
    "addion3": { "state": "0", "content": {} },
    "addion4": { "state": "0", "content": {} },
    "comment": "",
    "totalPrice": 5,
    "size": "1"
  },
  {
    "id": 9,
    "amount": 1,
    "category": "FamilyMeals",
    "title": "وجبات عائليه",
    "price": 5,
    "img": "/assets/famely.jpg",
    "description": "وجبات سريعه ,ايطالي",
    "addion1": { "state": "0", "content": {} },
    "addion2": { "state": "0", "content": {} },
    "addion3": { "state": "0", "content": {} },
    "addion4": { "state": "0", "content": {} },
    "comment": "",
    "totalPrice": 5,
    "size": "1"
  },
  {
    "id": 10,
    "category": "Shawarma",
    "title": "شاورما",
    "price": 5,
    "amount": 1,
    "img": "/assets/shawrma.jpg",
    "description": "وجبات سريعه ,ايطالي",
    "addion1": { "state": "0", "content": {} },
    "addion2": { "state": "0", "content": {} },
    "addion3": { "state": "0", "content": {} },
    "addion4": { "state": "0", "content": {} },
    "comment": "",
    "totalPrice": 5,
    "size": "1"
  },
  {
    "id": 11,
    "category": "casseroles",
    "amount": 1,
    "title": "طواجن",
    "price": 5,
    "img": "/assets/برجر.jpg",
    "description": "وجبات سريعه ,ايطالي",
    "addion1": { "state": "0", "content": {} },
    "addion2": { "state": "0", "content": {} },
    "addion3": { "state": "0", "content": {} },
    "addion4": { "state": "0", "content": {} },
    "comment": "",
    "totalPrice": 5,
    "size": "1"
  },
  {
    "id": 12,
    "category": "salads",
    "title": "سلطات ",
    "amount": 1,
    "price": 5,
    "img": "/assets/salata.jpg",
    "description": "وجبات سريعه ,ايطالي",
    "addion1": { "state": "0", "content": {} },
    "addion2": { "state": "0", "content": {} },
    "addion3": { "state": "0", "content": {} },
    "addion4": { "state": "0", "content": {} },
    "comment": "",
    "totalPrice": 5,
    "size": "1"
  },
  {
    "id": 13,
    "amount": 1,
    "category": "appetizers",
    "title": "مقبلات ",
    "price": 5,
    "img": "/assets/moqablat.jpg",
    "description": "وجبات سريعه ,ايطالي",
    "addion1": { "state": "0", "content": {} },
    "addion2": { "state": "0", "content": {} },
    "addion3": { "state": "0", "content": {} },
    "addion4": { "state": "0", "content": {} },
    "comment": "",
    "totalPrice": 5,
    "size": "1"
  },
  {
    "id": 14,
    "category": "SeeFood",
    "title": "مأكولات بحريه",
    "amount": 1,
    "price": 5,
    "img": "/assets/seefood.jpg",
    "description": "وجبات سريعه ,ايطالي",
    "addion1": { "state": "0", "content": {} },
    "addion2": { "state": "0", "content": {} },
    "addion3": { "state": "0", "content": {} },
    "addion4": { "state": "0", "content": {} },
    "comment": "",
    "totalPrice": 5,
    "size": "1"
  },
  {
    "id": 15,
    "amount": 1,
    "category": "MostWanted",
    "title": "الاكثر طلبا",
    "price": 5,
    "img": "/assets/meat.jpg",
    "description": "وجبات سريعه ,ايطالي",
    "addion1": { "state": "0", "content": {} },
    "addion2": { "state": "0", "content": {} },
    "addion3": { "state": "0", "content": {} },
    "addion4": { "state": "0", "content": {} },
    "comment": "",
    "totalPrice": 5,
    "size": "1"
  },
  {
    "id": 16,
    "category": "SeeFood",
    "amount": 1,
    "title": "مأكولات بحريه",
    "price": 5,
    "img": "/assets/SeeFood.jpg",
    "description": "وجبات سريعه ,ايطالي",
    "addion1": { "state": "0", "content": {} },
    "addion2": { "state": "0", "content": {} },
    "addion3": { "state": "0", "content": {} },
    "addion4": { "state": "0", "content": {} },
    "comment": "",
    "totalPrice": 5,
    "size": "1"
  },
  {
    "id": 17,
    "category": "Pizza",
    "title": "بيتزا",
    "amount": 1,
    "price": 5,
    "img": "/assets/petza.jpg",
    "description": "وجبات سريعه ,ايطالي",
    "addion1": { "state": "0", "content": {} },
    "addion2": { "state": "0", "content": {} },
    "addion3": { "state": "0", "content": {} },
    "addion4": { "state": "0", "content": {} },
    "comment": "",
    "totalPrice": 5,
    "size": "1"
  },
  {
    "id": 18,
    "category": "meat",
    "title": "لحوم",
    "amount": 1,
    "price": 5,
    "img": "/assets/meat.jpg",
    "description": "وجبات سريعه ,ايطالي",
    "addion1": { "state": "0", "content": {} },
    "addion2": { "state": "0", "content": {} },
    "addion3": { "state": "0", "content": {} },
    "addion4": { "state": "0", "content": {} },
    "comment": "",
    "totalPrice": 5,
    "size": "1"
  },
  {
    "id": 19,
    "category": "chicken",
    "amount": 1,
    "title": "فراخ",
    "price": 5,
    "img": "/assets/cheken.jpg",
    "description": "وجبات سريعه ,ايطالي",
    "addion1": { "state": "0", "content": {} },
    "addion2": { "state": "0", "content": {} },
    "addion3": { "state": "0", "content": {} },
    "addion4": { "state": "0", "content": {} },
    "comment": "",
    "totalPrice": 5,
    "size": "1"
  },
  {
    "id": 20,
    "category": "sandwichs",
    "title": "ساندوتشات",
    "amount": 1,
    "price": 5,
    "img": "/assets/sandwatch.jpg",
    "description": "وجبات سريعه ,ايطالي",
    "addion1": { "state": "0", "content": {} },
    "addion2": { "state": "0", "content": {} },
    "addion3": { "state": "0", "content": {} },
    "addion4": { "state": "0", "content": {} },
    "comment": "",
    "totalPrice": 5,
    "size": "1"
  },
  {
    "id": 21,
    "category": "Burger",
    "title": "برجر",
    "amount": 1,
    "price": 5,
    "img": "/assets/برجر.jpg",
    "description": "وجبات سريعه ,ايطالي",
    "addion1": { "state": "0", "content": {} },
    "addion2": { "state": "0", "content": {} },
    "addion3": { "state": "0", "content": {} },
    "addion4": { "state": "0", "content": {} },
    "comment": "",
    "totalPrice": 5,
    "size": "1"
  },
  {
    "id": 22,
    "amount": 1,
    "category": "FamilyMeals",
    "title": "وجبات عائليه",
    "price": 5,
    "img": "/assets/famely.jpg",
    "description": "وجبات سريعه ,ايطالي",
    "addion1": { "state": "0", "content": {} },
    "addion2": { "state": "0", "content": {} },
    "addion3": { "state": "0", "content": {} },
    "addion4": { "state": "0", "content": {} },
    "comment": "",
    "totalPrice": 5,
    "size": "1"
  },
  {
    "id": 23,
    "category": "Shawarma",
    "title": "شاورما",
    "amount": 1,
    "price": 5,
    "img": "/assets/shawrma.jpg",
    "description": "وجبات سريعه ,ايطالي",
    "addion1": { "state": "0", "content": {} },
    "addion2": { "state": "0", "content": {} },
    "addion3": { "state": "0", "content": {} },
    "addion4": { "state": "0", "content": {} },
    "comment": "",
    "totalPrice": 5,
    "size": "1"
  },
  {
    "id": 24,
    "category": "casseroles",
    "title": "طواجن",
    "amount": 1,
    "price": 5,
    "img": "/assets/برجر.jpg",
    "description": "وجبات سريعه ,ايطالي",
    "addion1": { "state": "0", "content": {} },
    "addion2": { "state": "0", "content": {} },
    "addion3": { "state": "0", "content": {} },
    "addion4": { "state": "0", "content": {} },
    "comment": "",
    "totalPrice": 5,
    "size": "1"
  },
  {
    "id": 25,
    "category": "salads",
    "title": "سلطات ",
    "amount": 1,
    "price": 5,
    "img": "/assets/salata.jpg",
    "description": "وجبات سريعه ,ايطالي",
    "addion1": { "state": "0", "content": {} },
    "addion2": { "state": "0", "content": {} },
    "addion3": { "state": "0", "content": {} },
    "addion4": { "state": "0", "content": {} },
    "comment": "",
    "totalPrice": 5,
    "size": "1"
  },
  {
    "id": 26,
    "category": "appetizers",
    "title": "مقبلات ",
    "amount": 1,
    "price": 5,
    "img": "/assets/moqablat.jpg",
    "description": "وجبات سريعه ,ايطالي",
    "addion1": { "state": "0", "content": {} },
    "addion2": { "state": "0", "content": {} },
    "addion3": { "state": "0", "content": {} },
    "addion4": { "state": "0", "content": {} },
    "comment": "",
    "totalPrice": 5,
    "size": "1"
  },
  {
    "id": 27,
    "category": "SeeFood",
    "amount": 1,
    "title": "مأكولات بحريه",
    "price": 5,
    "img": "/assets/SeeFood.jpg",
    "description": "وجبات سريعه ,ايطالي",
    "addion1": { "state": "0", "content": {} },
    "addion2": { "state": "0", "content": {} },
    "addion3": { "state": "0", "content": {} },
    "addion4": { "state": "0", "content": {} },
    "comment": "",
    "totalPrice": 5,
    "size": "1"
  },
  {
    "id": 28,
    "category": "MostWanted",
    "title": "الاكثر طلبا",
    "amount": 1,
    "price": 5,
    "img": "/assets/petza.jpg",
    "description": "وجبات سريعه ,ايطالي",
    "addion1": { "state": "0", "content": {} },
    "addion2": { "state": "0", "content": {} },
    "addion3": { "state": "0", "content": {} },
    "addion4": { "state": "0", "content": {} },
    "comment": "",
    "totalPrice": 5,
    "size": "1"
  },
  {
    "id": 29,
    "category": "SeeFood",
    "title": "مأكولات بحريه",
    "amount": 1,
    "price": 5,
    "img": "/assets/SeeFood.jpg",
    "description": "وجبات سريعه ,ايطالي",
    "addion1": { "state": "0", "content": {} },
    "addion2": { "state": "0", "content": {} },
    "addion3": { "state": "0", "content": {} },
    "addion4": { "state": "0", "content": {} },
    "comment": "",
    "totalPrice": 5,
    "size": "1"
  },
  {
    "id": 30,
    "category": "Pizza",
    "amount": 1,
    "title": "بيتزا",
    "price": 5,
    "img": "/assets/petza.jpg",
    "description": "وجبات سريعه ,ايطالي",
    "addion1": { "state": "0", "content": {} },
    "addion2": { "state": "0", "content": {} },
    "addion3": { "state": "0", "content": {} },
    "addion4": { "state": "0", "content": {} },
    "comment": "",
    "totalPrice": 5,
    "size": "1"
  },
  {
    "id": 31,
    "amount": 1,
    "category": "meat",
    "title": "لحوم",
    "price": 5,
    "img": "/assets/meat.jpg",
    "description": "وجبات سريعه ,ايطالي",
    "addion1": { "state": "0", "content": {} },
    "addion2": { "state": "0", "content": {} },
    "addion3": { "state": "0", "content": {} },
    "addion4": { "state": "0", "content": {} },
    "comment": "",
    "totalPrice": 5,
    "size": "1"
  },
  {
    "id": 32,
    "category": "chicken",
    "amount": 1,
    "title": "فراخ",
    "price": 5,
    "img": "/assets/cheken.jpg",
    "description": "وجبات سريعه ,ايطالي",
    "addion1": { "state": "0", "content": {} },
    "addion2": { "state": "0", "content": {} },
    "addion3": { "state": "0", "content": {} },
    "addion4": { "state": "0", "content": {} },
    "comment": "",
    "totalPrice": 5,
    "size": "1"
  },
  {
    "id": 33,
    "category": "sandwichs",
    "title": "ساندوتشات",
    "amount": 1,
    "price": 5,
    "img": "/assets/sandwatch.jpg",
    "description": "وجبات سريعه ,ايطالي",
    "addion1": { "state": "0", "content": {} },
    "addion2": { "state": "0", "content": {} },
    "addion3": { "state": "0", "content": {} },
    "addion4": { "state": "0", "content": {} },
    "comment": "",
    "totalPrice": 5,
    "size": "1"
  },
  {
    "id": 34,
    "category": "Burger",
    "title": "برجر",
    "price": 5,
    "amount": 1,
    "img": "/assets/برجر.jpg",
    "description": "وجبات سريعه ,ايطالي",
    "addion1": { "state": "0", "content": {} },
    "addion2": { "state": "0", "content": {} },
    "addion3": { "state": "0", "content": {} },
    "addion4": { "state": "0", "content": {} },
    "comment": "",
    "totalPrice": 5,
    "size": "1"
  },
  {
    "id": 35,
    "category": "FamilyMeals",
    "title": "وجبات عائليه",
    "price": 5,
    "amount": 1,
    "img": "/assets/famely.jpg",
    "description": "وجبات سريعه ,ايطالي",
    "addion1": { "state": "0", "content": {} },
    "addion2": { "state": "0", "content": {} },
    "addion3": { "state": "0", "content": {} },
    "addion4": { "state": "0", "content": {} },
    "comment": "",
    "totalPrice": 5,
    "size": "1"
  },
  {
    "id": 36,
    "category": "Shawarma",
    "title": "شاورما",
    "amount": 1,
    "price": 5,
    "img": "/assets/shawrma.jpg",
    "description": "وجبات سريعه ,ايطالي",
    "addion1": { "state": "0", "content": {} },
    "addion2": { "state": "0", "content": {} },
    "addion3": { "state": "0", "content": {} },
    "addion4": { "state": "0", "content": {} },
    "comment": "",
    "totalPrice": 5,
    "size": "1"
  },
  {
    "id": 37,
    "category": "casseroles",
    "amount": 1,
    "title": "طواجن",
    "price": 5,
    "img": "/assets/برجر.jpg",
    "description": "وجبات سريعه ,ايطالي",
    "addion1": { "state": "0", "content": {} },
    "addion2": { "state": "0", "content": {} },
    "addion3": { "state": "0", "content": {} },
    "addion4": { "state": "0", "content": {} },
    "comment": "",
    "totalPrice": 5,
    "size": "1"
  },
  {
    "id": 38,
    "category": "salads",
    "amount": 1,
    "title": "سلطات ",
    "price": 5,
    "img": "/assets/salata.jpg",
    "description": "وجبات سريعه ,ايطالي",
    "addion1": { "state": "0", "content": {} },
    "addion2": { "state": "0", "content": {} },
    "addion3": { "state": "0", "content": {} },
    "addion4": { "state": "0", "content": {} },
    "comment": "",
    "totalPrice": 5,
    "size": "1"
  },
  {
    "id": 39,
    "category": "appetizers",
    "amount": 1,
    "title": "مقبلات ",
    "price": 5,
    "img": "/assets/moqablat.jpg",
    "description": "وجبات سريعه ,ايطالي",
    "addion1": { "state": "0", "content": {} },
    "addion2": { "state": "0", "content": {} },
    "addion3": { "state": "0", "content": {} },
    "addion4": { "state": "0", "content": {} },
    "comment": "",
    "totalPrice": 5,
    "size": "1"
  },
  {
    "id": 40,
    "category": "SeeFood",
    "title": "مأكولات بحريه",
    "price": 5,
    "amount": 1,
    "img": "/assets/SeeFood.jpg",
    "description": "وجبات سريعه ,ايطالي",
    "addion1": { "state": "0", "content": {} },
    "addion2": { "state": "0", "content": {} },
    "addion3": { "state": "0", "content": {} },
    "addion4": { "state": "0", "content": {} },
    "comment": "",
    "totalPrice": 5,
    "size": "1"
  },
  {
    "id": 41,
    "category": "MostWanted",
    "title": "الاكثر طلبا",
    "price": 5,
    "amount": 1,
    "img": "/assets/cheken.jpg",
    "description": "وجبات سريعه ,ايطالي",
    "addion1": { "state": "0", "content": {} },
    "addion2": { "state": "0", "content": {} },
    "addion3": { "state": "0", "content": {} },
    "addion4": { "state": "0", "content": {} },
    "comment": "",
    "totalPrice": 5,
    "size": "1"
  },
  {
    "id": 42,
    "category": "SeeFood",
    "title": "مأكولات بحريه",
    "price": 5,
    "amount": 1,
    "img": "/assets/SeeFood.jpg",
    "description": "وجبات سريعه ,ايطالي",
    "addion1": { "state": "0", "content": {} },
    "addion2": { "state": "0", "content": {} },
    "addion3": { "state": "0", "content": {} },
    "addion4": { "state": "0", "content": {} },
    "comment": "",
    "totalPrice": 5,
    "size": "1"
  },
  {
    "id": 43,
    "category": "Pizza",
    "title": "بيتزا",
    "amount": 1,
    "price": 5,
    "img": "/assets/petza.jpg",
    "description": "وجبات سريعه ,ايطالي",
    "addion1": { "state": "0", "content": {} },
    "addion2": { "state": "0", "content": {} },
    "addion3": { "state": "0", "content": {} },
    "addion4": { "state": "0", "content": {} },
    "comment": "",
    "totalPrice": 5,
    "size": "1"
  },
  {
    "id": 44,
    "category": "meat",
    "title": "لحوم",
    "amount": 1,
    "price": 5,
    "img": "/assets/meat.jpg",
    "description": "وجبات سريعه ,ايطالي",
    "addion1": { "state": "0", "content": {} },
    "addion2": { "state": "0", "content": {} },
    "addion3": { "state": "0", "content": {} },
    "addion4": { "state": "0", "content": {} },
    "comment": "",
    "totalPrice": 5,
    "size": "1"
  },
  {
    "id": 45,
    "amount": 1,
    "category": "chicken",
    "title": "فراخ",
    "price": 5,
    "img": "/assets/cheken.jpg",
    "description": "وجبات سريعه ,ايطالي",
    "addion1": { "state": "0", "content": {} },
    "addion2": { "state": "0", "content": {} },
    "addion3": { "state": "0", "content": {} },
    "addion4": { "state": "0", "content": {} },
    "comment": "",
    "totalPrice": 5,
    "size": "1"
  },
  {
    "id": 46,
    "category": "sandwichs",
    "title": "ساندوتشات",
    "amount": 1,
    "img": "/assets/sandwatch.jpg",
    "description": "وجبات سريعه ,ايطالي",
    "addion1": { "state": "0", "content": {} },
    "addion2": { "state": "0", "content": {} },
    "addion3": { "state": "0", "content": {} },
    "addion4": { "state": "0", "content": {} },
    "comment": "",
    "totalPrice": 5,
    "size": "1"
  },
  {
    "id": 47,
    "category": "Burger",
    "amount": 1,
    "title": "برجر",
    "price": 5,
    "img": "/assets/برجر.jpg",
    "description": "وجبات سريعه ,ايطالي",
    "addion1": { "state": "0", "content": {} },
    "addion2": { "state": "0", "content": {} },
    "addion3": { "state": "0", "content": {} },
    "addion4": { "state": "0", "content": {} },
    "comment": "",
    "totalPrice": 5,
    "size": "1"
  },
  {
    "id": 48,
    "category": "FamilyMeals",
    "title": "وجبات عائليه",
    "amount": 1,
    "price": 5,
    "img": "/assets/famely.jpg",
    "description": "وجبات سريعه ,ايطالي",
    "addion1": { "state": "0", "content": {} },
    "addion2": { "state": "0", "content": {} },
    "addion3": { "state": "0", "content": {} },
    "addion4": { "state": "0", "content": {} },
    "comment": "",
    "totalPrice": 5,
    "size": "1"
  },
  {
    "id": 49,
    "amount": 1,
    "category": "Shawarma",
    "title": "شاورما",
    "price": 5,
    "img": "/assets/shawrma.jpg",
    "description": "وجبات سريعه ,ايطالي",
    "addion1": { "state": "0", "content": {} },
    "addion2": { "state": "0", "content": {} },
    "addion3": { "state": "0", "content": {} },
    "addion4": { "state": "0", "content": {} },
    "comment": "",
    "totalPrice": 5,
    "size": "1"
  },
  {
    "id": 50,
    "category": "casseroles",
    "title": "طواجن",
    "amount": 1,
    "price": 5,
    "img": "/assets/برجر.jpg",
    "description": "وجبات سريعه ,ايطالي",
    "addion1": { "state": "0", "content": {} },
    "addion2": { "state": "0", "content": {} },
    "addion3": { "state": "0", "content": {} },
    "addion4": { "state": "0", "content": {} },
    "comment": "",
    "totalPrice": 5,
    "size": "1"
  },
  {
    "id": 51,
    "amount": 1,
    "category": "hotDrinks",
    "title": "مشروبات ساخنه",
    "price": 5,
    "img": "./assets/hot.jpg",
    "description": "وجبات سريعه ,ايطالي",
    "addion1": { "state": "0", "content": {} },
    "addion2": { "state": "0", "content": {} },
    "addion3": { "state": "0", "content": {} },
    "addion4": { "state": "0", "content": {} },
    "comment": "",
    "totalPrice": 5,
    "size": "1"
  },
  {
    "id": 52,
    "amount": 1,
    "category": "hotDrinks",
    "title": "مشروبات ساخنه",
    "price": 5,
    "img": "/assets/hot.jpg",
    "description": "وجبات سريعه ,ايطالي",
    "addion1": { "state": "0", "content": {} },
    "addion2": { "state": "0", "content": {} },
    "addion3": { "state": "0", "content": {} },
    "addion4": { "state": "0", "content": {} },
    "comment": "",
    "totalPrice": 5,
    "size": "1"
  },
  {
    "id": 53,
    "category": "hotDrinks",
    "amount": 1,
    "title": "مشروبات ساخنه",
    "price": 5,
    "img": "/assets/hot.jpg",
    "description": "وجبات سريعه ,ايطالي",
    "addion1": { "state": "0", "content": {} },
    "addion2": { "state": "0", "content": {} },
    "addion3": { "state": "0", "content": {} },
    "addion4": { "state": "0", "content": {} },
    "comment": "",
    "totalPrice": 5,
    "size": "1"
  },
  {
    "id": 54,
    "category": "hotDrinks",
    "title": "مشروبات ساخنه",
    "amount": 1,
    "price": 5,
    "img": "/assets/hot.jpg",
    "description": "وجبات سريعه ,ايطالي",
    "addion1": { "state": "0", "content": {} },
    "addion2": { "state": "0", "content": {} },
    "addion3": { "state": "0", "content": {} },
    "addion4": { "state": "0", "content": {} },
    "comment": "",
    "totalPrice": 5,
    "size": "1"
  },
  {
    "id": 55,
    "category": "hotDrinks",
    "title": "مشروبات ساخنه",
    "price": "5 ",
    "amount": 1,
    "img": "/assets/hot.jpg",
    "description": "وجبات سريعه ,ايطالي",
    "addion1": { "state": "0", "content": {} },
    "addion2": { "state": "0", "content": {} },
    "addion3": { "state": "0", "content": {} },
    "addion4": { "state": "0", "content": {} },
    "comment": "",
    "totalPrice": 5,
    "size": "1"
  },
  {
    "id": 56,
    "category": "coldDrinks",
    "title": "مشروبات بارده",
    "amount": 1,
    "price": "5 ",
    "img": "/assets/cold.jpg",
    "description": "وجبات سريعه ,ايطالي",
    "addion1": { "state": "0", "content": {} },
    "addion2": { "state": "0", "content": {} },
    "addion3": { "state": "0", "content": {} },
    "addion4": { "state": "0", "content": {} },
    "comment": "",
    "totalPrice": 5,
    "size": "1"
  },
  {
    "id": 57,
    "category": "coldDrinks",
    "title": "مشروبات بارده",
    "price": "5 ",
    "amount": 1,
    "img": "/assets/cold.jpg",
    "description": "وجبات سريعه ,ايطالي",
    "addion1": { "state": "0", "content": {} },
    "addion2": { "state": "0", "content": {} },
    "addion3": { "state": "0", "content": {} },
    "addion4": { "state": "0", "content": {} },
    "comment": "",
    "totalPrice": 5,
    "size": "1"
  },
  {
    "id": 58,
    "category": "coldDrinks",
    "amount": 1,
    "title": "مشروبات بارده",
    "price": 5,
    "img": "/assets/cold.jpg",
    "description": "وجبات سريعه ,ايطالي",
    "addion1": { "state": "0", "content": {} },
    "addion2": { "state": "0", "content": {} },
    "addion3": { "state": "0", "content": {} },
    "addion4": { "state": "0", "content": {} },
    "comment": "",
    "totalPrice": 5,
    "size": "1"
  },
  {
    "id": 59,
    "category": "coldDrinks",
    "title": "مشروبات بارده",
    "amount": 1,
    "price": 5,
    "img": "/assets/cold.jpg",
    "description": "وجبات سريعه ,ايطالي",
    "addion1": { "state": "0", "content": {} },
    "addion2": { "state": "0", "content": {} },
    "addion3": { "state": "0", "content": {} },
    "addion4": { "state": "0", "content": {} },
    "comment": "",
    "totalPrice": 5,
    "size": "1"
  },
  {
    "id": 60,
    "category": "coldDrinks",
    "title": "مشروبات بارده",
    "amount": 1,
    "price": 5,
    "img": "/assets/cold.jpg",
    "description": "وجبات سريعه ,ايطالي",
    "addion1": { "state": "0", "content": {} },
    "addion2": { "state": "0", "content": {} },
    "addion3": { "state": "0", "content": {} },
    "addion4": { "state": "0", "content": {} },
    "comment": "",
    "totalPrice": 5,
    "size": "1"
  }
]
